README
setup.py
django_tiniest_cms/__init__.py
django_tiniest_cms/admin.py
django_tiniest_cms/models.py
django_tiniest_cms/tests.py
django_tiniest_cms.egg-info/PKG-INFO
django_tiniest_cms.egg-info/SOURCES.txt
django_tiniest_cms.egg-info/dependency_links.txt
django_tiniest_cms.egg-info/requires.txt
django_tiniest_cms.egg-info/top_level.txt
django_tiniest_cms/templatetags/__init__.py
django_tiniest_cms/templatetags/tiniest_cms.py