Metadata-Version: 1.0
Name: django-tiniest-cms
Version: 0.9.1
Summary: django-tiniest-cms is a seriously minimalist Django CMS
Home-page: https://github.com/Gautier/django-tiniest-cms
Author: Gautier Hayoun
Author-email: ghayoun@gmail.com
License: MIT
Platform: UNKNOWN
